<?xml version="1.0" encoding="UTF-8"?><record_update table="ais_search_profile_ais_search_source_m2m">
    <ais_search_profile_ais_search_source_m2m action="DELETE">
        <exclude_attachments_in_now_assist_genius_results>false</exclude_attachments_in_now_assist_genius_results>
        <exclude_in_now_assist_genius_results>false</exclude_in_now_assist_genius_results>
        <exclude_in_regular_search>false</exclude_in_regular_search>
        <profile display_value="HCLS Medical Imagining Email Review getHealthServiceDefinition NASK Created">6dfb4ff193ee32509634f3990103d69b</profile>
        <search_source display_value="NASK Created HCLS Medical Imagining Email Review getHealthServiceDefinition Service Definition">e1fb4b7d93ae32509634f3990103d6d7</search_source>
        <sys_class_name>ais_search_profile_ais_search_source_m2m</sys_class_name>
        <sys_created_by>admin</sys_created_by>
        <sys_created_on>2026-01-21 00:58:35</sys_created_on>
        <sys_id>61fb4ff193ee32509634f3990103d6b6</sys_id>
        <sys_mod_count>0</sys_mod_count>
        <sys_name>HCLS Medical Imagining Email Review getHealthServiceDefinition NASK Created.NASK Created HCLS Medical Imagining Email Review getHealthServiceDefinition Service Definition</sys_name>
        <sys_package display_value="Pete's Email Engagement Toolkit" source="x_snc_pab_ee_tkit">01900de693acba502e03fde1a903d651</sys_package>
        <sys_policy/>
        <sys_scope display_value="Pete's Email Engagement Toolkit">01900de693acba502e03fde1a903d651</sys_scope>
        <sys_update_name>ais_search_profile_ais_search_source_m2m_61fb4ff193ee32509634f3990103d6b6</sys_update_name>
        <sys_updated_by>admin</sys_updated_by>
        <sys_updated_on>2026-01-21 00:58:35</sys_updated_on>
    </ais_search_profile_ais_search_source_m2m>
    <sys_update_version action="INSERT_OR_UPDATE">
        <action>DELETE</action>
        <application display_value="Pete's Email Engagement Toolkit">01900de693acba502e03fde1a903d651</application>
        <file_path/>
        <instance_id>6ef21738fbce36dc0c92f633beefdc6a</instance_id>
        <instance_name>demoalectrihclszu136922</instance_name>
        <name>ais_search_profile_ais_search_source_m2m_61fb4ff193ee32509634f3990103d6b6</name>
        <payload><![CDATA[<?xml version="1.0" encoding="UTF-8"?><record_update table="ais_search_profile_ais_search_source_m2m"><ais_search_profile_ais_search_source_m2m action="INSERT_OR_UPDATE"><exclude_attachments_in_now_assist_genius_results>false</exclude_attachments_in_now_assist_genius_results><exclude_in_now_assist_genius_results>false</exclude_in_now_assist_genius_results><exclude_in_regular_search>false</exclude_in_regular_search><profile display_value="HCLS Medical Imagining Email Review getHealthServiceDefinition NASK Created">6dfb4ff193ee32509634f3990103d69b</profile><search_source display_value="NASK Created HCLS Medical Imagining Email Review getHealthServiceDefinition Service Definition">e1fb4b7d93ae32509634f3990103d6d7</search_source><sys_class_name>ais_search_profile_ais_search_source_m2m</sys_class_name><sys_created_by>admin</sys_created_by><sys_created_on>2026-01-21 00:58:35</sys_created_on><sys_id>61fb4ff193ee32509634f3990103d6b6</sys_id><sys_mod_count>0</sys_mod_count><sys_name>HCLS Medical Imagining Email Review getHealthServiceDefinition NASK Created.NASK Created HCLS Medical Imagining Email Review getHealthServiceDefinition Service Definition</sys_name><sys_package display_value="Pete's Email Engagement Toolkit" source="x_snc_pab_ee_tkit">01900de693acba502e03fde1a903d651</sys_package><sys_policy/><sys_scope display_value="Pete's Email Engagement Toolkit">01900de693acba502e03fde1a903d651</sys_scope><sys_update_name>ais_search_profile_ais_search_source_m2m_61fb4ff193ee32509634f3990103d6b6</sys_update_name><sys_updated_by>admin</sys_updated_by><sys_updated_on>2026-01-21 00:58:35</sys_updated_on></ais_search_profile_ais_search_source_m2m></record_update>]]></payload>
        <payload_hash>-1953228080</payload_hash>
        <record_name>HCLS Medical Imagining Email Review getHealthServiceDefinition NASK Created.NASK Created HCLS Medica</record_name>
        <reverted_from/>
        <source>09927d20936af6509634f3990103d697</source>
        <source_table>sys_update_set</source_table>
        <state>previous</state>
        <sys_created_by>admin</sys_created_by>
        <sys_created_on>2026-01-21 00:58:36</sys_created_on>
        <sys_id>e1fb8ff193ee32509634f3990103d602</sys_id>
        <sys_mod_count>0</sys_mod_count>
        <sys_recorded_at>19bde0f7ef20000001</sys_recorded_at>
        <sys_updated_by>admin</sys_updated_by>
        <sys_updated_on>2026-01-21 00:58:36</sys_updated_on>
        <type>AI Search Search Profile Search Source M</type>
        <update_guid>21fb8ff1adee3250747022d0d78a8501</update_guid>
        <update_guid_history>21fb8ff1adee3250747022d0d78a8501:-1953228080</update_guid_history>
    </sys_update_version>
    <sys_metadata_delete action="INSERT_OR_UPDATE">
        <sys_audit_delete display_value="HCLS Medical Imagining Email Review getHealthServiceDefinition NASK Created.NASK">863f4f71936272509634f3990103d6a6</sys_audit_delete>
        <sys_class_name>sys_metadata_delete</sys_class_name>
        <sys_created_by>admin</sys_created_by>
        <sys_created_on>2026-01-21 01:12:49</sys_created_on>
        <sys_db_object display_value="" name="ais_search_profile_ais_search_source_m2m">ais_search_profile_ais_search_source_m2m</sys_db_object>
        <sys_id>16c47e183a6c4e6ca07d9b1c38870f10</sys_id>
        <sys_metadata>61fb4ff193ee32509634f3990103d6b6</sys_metadata>
        <sys_mod_count>0</sys_mod_count>
        <sys_name>HCLS Medical Imagining Email Review getHealthServiceDefinition NASK Created.NASK Created HCLS Medical Imagining Email Review getHealthServiceDefinition Service Definition</sys_name>
        <sys_package display_value="Pete's Email Engagement Toolkit" source="x_snc_pab_ee_tkit">01900de693acba502e03fde1a903d651</sys_package>
        <sys_parent/>
        <sys_policy/>
        <sys_scope display_value="Pete's Email Engagement Toolkit">01900de693acba502e03fde1a903d651</sys_scope>
        <sys_scope_delete display_value="">7f3c4b3b187c476ea20507635850af84</sys_scope_delete>
        <sys_update_name>ais_search_profile_ais_search_source_m2m_61fb4ff193ee32509634f3990103d6b6</sys_update_name>
        <sys_update_version display_value="ais_search_profile_ais_search_source_m2m_61fb4ff193ee32509634f3990103d6b6">e1fb8ff193ee32509634f3990103d602</sys_update_version>
        <sys_updated_by>admin</sys_updated_by>
        <sys_updated_on>2026-01-21 01:12:49</sys_updated_on>
    </sys_metadata_delete>
</record_update>
